schema_classification/__init__.py
schema_classification/bp/__init__.py
schema_classification/bp/schema_orchestrator.py
schema_classification/dmo/__init__.py
schema_classification/dmo/confidence_exclude_allof.py
schema_classification/dmo/confidence_include_allof.py
schema_classification/dmo/filter_exclude_allof.py
schema_classification/dmo/filter_exclude_oneof.py
schema_classification/dmo/filter_include_allof.py
schema_classification/dmo/filter_include_oneof.py
schema_classification/dmo/filter_startswith.py
schema_classification/dmo/index_exclude_allof.py
schema_classification/dmo/index_exclude_oneof.py
schema_classification/dmo/index_include_allof.py
schema_classification/dmo/index_include_oneof.py
schema_classification/dmo/index_scoring.py
schema_classification/dmo/index_startswith.py
schema_classification/dto/__init__.py
schema_classification/dto/typedefs.py
schema_classification/svc/__init__.py
schema_classification/svc/filter_mapping.py
schema_classification/svc/read_mapping.py
schema_classification/svc/select_mapping.py
schema_classification-0.1.8.dist-info/WHEEL
schema_classification-0.1.8.dist-info/METADATA
schema_classification-0.1.8.dist-info/RECORD
