Metadata-Version: 2.1
Name: schema-classification
Version: 0.1.8
Summary: Perform Intent Classification using an External Schema
Home-page: https://github.com/craigtrim/schema-classification
License: None
Keywords: nlp,nlu,ai,classification,intents
Author: Craig Trim
Author-email: craigtrim@gmail.com
Maintainer: Craig Trim
Maintainer-email: craigtrim@gmail.com
Requires-Python: >=3.8.5,<4.0.0
Classifier: Development Status :: 4 - Beta
Classifier: License :: Other/Proprietary License
Classifier: Programming Language :: Python :: 3
Classifier: Programming Language :: Python :: 3.10
Classifier: Programming Language :: Python :: 3.9
Classifier: Topic :: Scientific/Engineering :: Artificial Intelligence
Classifier: Topic :: Software Development :: Libraries :: Python Modules
Requires-Dist: baseblock
Project-URL: Repository, https://github.com/craigtrim/schema-classification
